[
    {
        "id": "01",
        "name": "What are bikepacking bags and how do you pack them?",
        "date": "Nov 3, 2021",
        "img": "https://i.ibb.co/VDXFWk5/news1.jpg"
    },
    {
        "id": "02",
        "name": "Gunn-Rita Dahle Flesjå’s five top tips for your first cross-country race",
        "date": "Nov 2, 2021",
        "img": "https://i.ibb.co/ZSJnyWG/new2.jpg"
    },
    {
        "id": "03",
        "name": "Dave's 586km, 37 hour EPIC charity ride across the length of Wales - twice",
        "date": "Nov 1, 2021",
        "img": "https://i.ibb.co/ph3y8Hc/news3.jpg"
    }
]